[
  {
    "ContainingType": "WEBPROGM.Controllers.AlbumController",
    "Method": "GetAlbums",
    "RelativePath": "api/Album",
    "HttpMethod": "GET",
    "IsController": true,
    "Order": 0,
    "Parameters": [],
    "ReturnTypes": [
      {
        "Type": "System.Collections.Generic.IEnumerable\u00601[[Back.Models.ItemCard, Back, Version=1.0.0.0, Culture=neutral, PublicKeyToken=null]]",
        "MediaTypes": [
          "text/plain",
          "application/json",
          "text/json"
        ],
        "StatusCode": 200
      }
    ]
  },
  {
    "ContainingType": "WEBPROGM.Controllers.AlbumController",
    "Method": "CreateAlbum",
    "RelativePath": "api/Album",
    "HttpMethod": "POST",
    "IsController": true,
    "Order": 0,
    "Parameters": [
      {
        "Name": "album",
        "Type": "Back.Models.ItemCard",
        "IsRequired": true
      }
    ],
    "ReturnTypes": [
      {
        "Type": "Back.Models.ItemCard",
        "MediaTypes": [
          "text/plain",
          "application/json",
          "text/json"
        ],
        "StatusCode": 200
      }
    ]
  },
  {
    "ContainingType": "WEBPROGM.Controllers.AlbumController",
    "Method": "GetAlbumById",
    "RelativePath": "api/Album/{id}",
    "HttpMethod": "GET",
    "IsController": true,
    "Order": 0,
    "Parameters": [
      {
        "Name": "id",
        "Type": "System.Int32",
        "IsRequired": true
      }
    ],
    "ReturnTypes": [
      {
        "Type": "System.Collections.Generic.IEnumerable\u00601[[Back.Models.ItemCard, Back, Version=1.0.0.0, Culture=neutral, PublicKeyToken=null]]",
        "MediaTypes": [
          "text/plain",
          "application/json",
          "text/json"
        ],
        "StatusCode": 200
      }
    ]
  },
  {
    "ContainingType": "WEBPROGM.Controllers.AlbumController",
    "Method": "UpdateStock",
    "RelativePath": "api/Album/{productId}",
    "HttpMethod": "PATCH",
    "IsController": true,
    "Order": 0,
    "Parameters": [
      {
        "Name": "productId",
        "Type": "System.Int32",
        "IsRequired": true
      },
      {
        "Name": "stock",
        "Type": "System.Int32",
        "IsRequired": true
      }
    ],
    "ReturnTypes": []
  },
  {
    "ContainingType": "WEBPROGM.Controllers.InventoryController",
    "Method": "GetInventory",
    "RelativePath": "api/Inventory",
    "HttpMethod": "GET",
    "IsController": true,
    "Order": 0,
    "Parameters": [],
    "ReturnTypes": [
      {
        "Type": "System.Collections.Generic.IEnumerable\u00601[[Back.Models.ItemCard, Back, Version=1.0.0.0, Culture=neutral, PublicKeyToken=null]]",
        "MediaTypes": [
          "text/plain",
          "application/json",
          "text/json"
        ],
        "StatusCode": 200
      }
    ]
  },
  {
    "ContainingType": "WEBPROGM.Controllers.InventoryController",
    "Method": "AddToInventory",
    "RelativePath": "api/Inventory",
    "HttpMethod": "POST",
    "IsController": true,
    "Order": 0,
    "Parameters": [
      {
        "Name": "item",
        "Type": "Back.Models.ItemCard",
        "IsRequired": true
      }
    ],
    "ReturnTypes": [
      {
        "Type": "Back.Models.ItemCard",
        "MediaTypes": [
          "text/plain",
          "application/json",
          "text/json"
        ],
        "StatusCode": 200
      }
    ]
  },
  {
    "ContainingType": "WEBPROGM.Controllers.OrderController",
    "Method": "CreateOrder",
    "RelativePath": "api/Order",
    "HttpMethod": "POST",
    "IsController": true,
    "Order": 0,
    "Parameters": [
      {
        "Name": "newOrder",
        "Type": "Back.Models.Order",
        "IsRequired": true
      }
    ],
    "ReturnTypes": [
      {
        "Type": "Back.Models.Order",
        "MediaTypes": [
          "text/plain",
          "application/json",
          "text/json"
        ],
        "StatusCode": 200
      }
    ]
  },
  {
    "ContainingType": "WEBPROGM.Controllers.OrderController",
    "Method": "GetOrderById",
    "RelativePath": "api/Order/{orderId}",
    "HttpMethod": "GET",
    "IsController": true,
    "Order": 0,
    "Parameters": [
      {
        "Name": "orderId",
        "Type": "System.Int32",
        "IsRequired": true
      }
    ],
    "ReturnTypes": [
      {
        "Type": "Back.Models.Order",
        "MediaTypes": [
          "text/plain",
          "application/json",
          "text/json"
        ],
        "StatusCode": 200
      }
    ]
  },
  {
    "ContainingType": "UserController",
    "Method": "GetUser",
    "RelativePath": "api/User/{userId}",
    "HttpMethod": "GET",
    "IsController": true,
    "Order": 0,
    "Parameters": [
      {
        "Name": "userId",
        "Type": "System.Int32",
        "IsRequired": true
      }
    ],
    "ReturnTypes": [
      {
        "Type": "Back.Models.Client",
        "MediaTypes": [
          "text/plain",
          "application/json",
          "text/json"
        ],
        "StatusCode": 200
      }
    ]
  },
  {
    "ContainingType": "UserController",
    "Method": "AddToShoppingCart",
    "RelativePath": "api/User/{userId}/shoppingcart",
    "HttpMethod": "POST",
    "IsController": true,
    "Order": 0,
    "Parameters": [
      {
        "Name": "userId",
        "Type": "System.Int32",
        "IsRequired": true
      },
      {
        "Name": "productId",
        "Type": "System.Int32",
        "IsRequired": true
      }
    ],
    "ReturnTypes": []
  },
  {
    "ContainingType": "UserController",
    "Method": "Login",
    "RelativePath": "api/User/login",
    "HttpMethod": "POST",
    "IsController": true,
    "Order": 0,
    "Parameters": [
      {
        "Name": "loginUser",
        "Type": "Back.Models.Client",
        "IsRequired": true
      }
    ],
    "ReturnTypes": [
      {
        "Type": "Back.Models.Client",
        "MediaTypes": [
          "text/plain",
          "application/json",
          "text/json"
        ],
        "StatusCode": 200
      }
    ]
  },
  {
    "ContainingType": "UserController",
    "Method": "RegisterUser",
    "RelativePath": "api/User/register",
    "HttpMethod": "POST",
    "IsController": true,
    "Order": 0,
    "Parameters": [
      {
        "Name": "newUser",
        "Type": "Back.Models.Client",
        "IsRequired": true
      }
    ],
    "ReturnTypes": [
      {
        "Type": "Back.Models.Client",
        "MediaTypes": [
          "text/plain",
          "application/json",
          "text/json"
        ],
        "StatusCode": 200
      }
    ]
  }
]